setup.cfg
setup.py
cube/__init__.py
cube/api.py
cube/utils.py
cube.egg-info/PKG-INFO
cube.egg-info/SOURCES.txt
cube.egg-info/dependency_links.txt
cube.egg-info/top_level.txt