Metadata-Version: 1.1
Name: cube
Version: 0.0.2
Summary: Python bindings for interfacing with Cube.
Home-page: https://docs.cube.ai/
Author: CubeAI
Author-email: mat@cube.ai
License: UNKNOWN
Keywords: cube api
Platform: UNKNOWN
Classifier: Development Status :: 4 - Beta
Classifier: Intended Audience :: Developers
Classifier: Programming Language :: Python :: 2.7
Classifier: Natural Language :: English
Classifier: Operating System :: OS Independent
Classifier: Topic :: Scientific/Engineering :: Artificial Intelligence
